sql_cli/__init__.py
sql_cli/sql_cli.py
very_basic_sql_builder-1.0.7.dist-info/DESCRIPTION.rst
very_basic_sql_builder-1.0.7.dist-info/METADATA
very_basic_sql_builder-1.0.7.dist-info/RECORD
very_basic_sql_builder-1.0.7.dist-info/WHEEL
very_basic_sql_builder-1.0.7.dist-info/entry_points.txt
very_basic_sql_builder-1.0.7.dist-info/metadata.json
very_basic_sql_builder-1.0.7.dist-info/top_level.txt
