Metadata-Version: 2.0
Name: very-basic-sql-builder
Version: 1.0.7
Summary: UNKNOWN
Home-page: UNKNOWN
Author: UNKNOWN
Author-email: UNKNOWN
License: UNKNOWN
Platform: UNKNOWN
Requires-Dist: Click
